ditz/__init__.py
ditz/__main__.py
ditz/colorize.py
ditz/commands.py
ditz/config.py
ditz/console.py
ditz/database.py
ditz/display.py
ditz/editor.py
ditz/exporter.py
ditz/files.py
ditz/flags.py
ditz/logger.py
ditz/objects.py
ditz/plugin.py
ditz/schemas.py
ditz/session.py
ditz/settings.py
ditz/term.py
ditz/util.py
ditz/vcs.py
ditz/command/__init__.py
ditz/command/builtin.py
ditz/command/info.py
ditz/command/issue.py
ditz/command/project.py
ditz/command/utils.py
ditz/docopt/__init__.py
ditz/docopt/doccmd.py
ditz/docopt/docopt.py
ditz/docopt/docoptions.py
pyditz-0.11.dist-info/COPYING
pyditz-0.11.dist-info/METADATA
pyditz-0.11.dist-info/WHEEL
pyditz-0.11.dist-info/entry_points.txt
pyditz-0.11.dist-info/top_level.txt
pyditz-0.11.dist-info/RECORD
