Metadata-Version: 2.1
Name: pyditz
Version: 0.11
Summary: Python implementation of Ditz (http://rubygems.org/gems/ditz).
Home-page: http://pypi.python.org/pypi/pyditz
Author: Glenn Hutchings
Author-email: zondo42@gmail.com
License: LGPL v2 or later
Platform: UNKNOWN
Classifier: Development Status :: 4 - Beta
Classifier: Environment :: Console
Classifier: Intended Audience :: Developers
Classifier: License :: OSI Approved :: GNU Lesser General Public License v2 or later (LGPLv2+)
Classifier: Natural Language :: English
Classifier: Operating System :: Microsoft :: Windows
Classifier: Operating System :: POSIX :: Linux
Classifier: Operating System :: Unix
Classifier: Programming Language :: Python :: 2.7
Classifier: Programming Language :: Python :: 3
Classifier: Programming Language :: Python :: 3.6
Classifier: Topic :: Software Development :: Bug Tracking
Requires-Dist: pyyaml
Requires-Dist: cerberus
Requires-Dist: jinja2
Requires-Dist: six
